heapgeneratorq/__init__.py
heapgeneratorq/l1.py
heapgeneratorq-0.1.0.dist-info/licenses/LICENSE
heapgeneratorq-0.1.0.dist-info/METADATA
heapgeneratorq-0.1.0.dist-info/WHEEL
heapgeneratorq-0.1.0.dist-info/top_level.txt
heapgeneratorq-0.1.0.dist-info/RECORD
