Metadata-Version: 2.4
Name: heapgeneratorq
Version: 0.1.0
Summary: A comprehensive collection of algorithms and data structures implementations
Home-page: https://github.com/DevankU/heapgeneratorq
Author: Devank U
Author-email: Devank U <devank@example.com>
License: MIT
Project-URL: Homepage, https://github.com/DevankU/heapgeneratorq
Project-URL: Bug Tracker, https://github.com/DevankU/heapgeneratorq/issues
Classifier: Development Status :: 3 - Alpha
Classifier: Intended Audience :: Developers
Classifier: Intended Audience :: Education
Classifier: Topic :: Software Development :: Libraries :: Python Modules
Classifier: Topic :: Education
Classifier: License :: OSI Approved :: MIT License
Classifier: Programming Language :: Python :: 3
Classifier: Programming Language :: Python :: 3.7
Classifier: Programming Language :: Python :: 3.8
Classifier: Programming Language :: Python :: 3.9
Classifier: Programming Language :: Python :: 3.10
Classifier: Programming Language :: Python :: 3.11
Requires-Python: >=3.7
License-File: LICENSE
Dynamic: author
Dynamic: home-page
Dynamic: license-file
Dynamic: requires-python
